<registry
  xmlns:i18n="http://xml.zope.org/namespaces/i18n">
  <record field="delay"
          interface="collective.contentrules.comingsoon.interfaces.IComingSoonSettings"
          name="collective.contentrules.comingsoon.interfaces.IComingSoonSettings.delay"
          i18n:domain="collective.contentrules.comingsoon">
     <field type="plone.registry.field.Int">
         <title>Default delay</title>
         <description>help_comingsoon_delay</description>
         <min>0</min>
     </field>
     <value>1</value>
  </record>
  <record field="delays"
          interface="collective.contentrules.comingsoon.interfaces.IComingSoonSettings"
          name="collective.contentrules.comingsoon.interfaces.IComingSoonSettings.delays"
          i18n:domain="collective.contentrules.comingsoon">
     <field type="plone.registry.field.List">
         <title>Per content types delays</title>
         <description>help_comingsoon_delays</description>
     </field>
  </record>
</registry>